artifactory_cleanup/__init__.py
artifactory_cleanup/artifactorycleanup.py
artifactory_cleanup/base_url_session.py
artifactory_cleanup/cli.py
artifactory_cleanup/context_managers.py
artifactory_cleanup/errors.py
artifactory_cleanup/loaders.py
artifactory_cleanup/rules/__init__.py
artifactory_cleanup/rules/base.py
artifactory_cleanup/rules/delete.py
artifactory_cleanup/rules/docker.py
artifactory_cleanup/rules/filters.py
artifactory_cleanup/rules/keep.py
artifactory_cleanup/rules/repo.py
artifactory_cleanup/rules/utils.py
artifactory_cleanup-1.0.18.dist-info/licenses/LICENSE
artifactory_cleanup-1.0.18.dist-info/METADATA
artifactory_cleanup-1.0.18.dist-info/WHEEL
artifactory_cleanup-1.0.18.dist-info/entry_points.txt
artifactory_cleanup-1.0.18.dist-info/top_level.txt
artifactory_cleanup-1.0.18.dist-info/RECORD
