Metadata-Version: 2.4
Name: artifactory-cleanup
Version: 1.0.18
Summary: Rules and cleanup policies for Artifactory
Home-page: https://github.com/devopshq/artifactory-cleanup
Author: Alexey Burov
Author-email: allburov@gmail.com
License: MIT
Keywords: DevOpsHQ
Classifier: Development Status :: 5 - Production/Stable
Classifier: Intended Audience :: Developers
Classifier: Topic :: Software Development :: Libraries :: Python Modules
Classifier: License :: OSI Approved :: MIT License
Classifier: Natural Language :: English
Classifier: Programming Language :: Python :: 3.6
Classifier: Programming Language :: Python :: 3.7
Requires-Python: >=3.6
License-File: LICENSE
Requires-Dist: hurry.filesize
Requires-Dist: prettytable
Requires-Dist: plumbum
Requires-Dist: dohq-artifactory
Requires-Dist: teamcity-messages
Requires-Dist: treelib
Requires-Dist: attrs
Requires-Dist: pydash
Requires-Dist: pyyaml
Requires-Dist: cfgv~=3.3
Requires-Dist: typing-extensions; python_version < "3.8.0"
Dynamic: author
Dynamic: author-email
Dynamic: classifier
Dynamic: description
Dynamic: description-content-type
Dynamic: home-page
Dynamic: keywords
Dynamic: license
Dynamic: license-file
Dynamic: requires-dist
Dynamic: requires-python
Dynamic: summary
